{"dEZbXD/+lEM2wP0oXoujxA==":"mbr-1620x1080.jpg","pnhbkets1GJZv1jAI3Gs5A==":"mbr-1920x947.jpg","CwDIl9SYma2zJIRGGqithw==":"mbr-1440x1080.jpg","cOSFvVm0As2Q5ucSZmR0MA==":"mbr-721x1080.jpg","14boR460t4rjf3MMJQo5VQ==":"mbr-1-1620x1080.jpg","Zdv1O5IVFe25tebN+Cr+1w==":"mbr-1619x1080.jpg","TTSeoCs4AzlRZoFHpZ6n6w==":"mbr-2-1620x1080.jpg","n6ymo7Em3hUztTQgW9NUeQ==":"mbr-3-1620x1080.jpg","vXGLBHrL+x0+RyzWvghKhQ==":"mbr-1618x1080.jpg","jJrtHRJwZwZOeNOe2BxzgA==":"mbr-4-1620x1080.jpg","uv6zaZyvhhIVHWy5oo0Yqw==":"mbr-1696x1080.jpg","Cah+vRrKBNCbNYfR6kRmVg==":"mbr-5-1620x1080.jpg","uGXvaFGhzoZmApoyNmlVlw==":"mbr-6-1620x1080.jpg","+Gm3ELe4XTy2R4if4L8TIg==":"mbr-7-1620x1080.jpg","PUM0bo5oOgecoYXXoKhJQg==":"mbr-8-1620x1080.jpg","2I/oeaPS33K1qG0fdiOx5Q==":"sm-logo-header-122x118.png","3tiimAb6umEGOol/03fuYw==":"mbr-720x1080.jpg","BjLWyPUX4EI4pMMsR93o0A==":"voiceagent-2000x1328.jpg","87g4Vrg2lI8tyi83mf7zgw==":"untitled-2-2000x1200.png","map4p+1WbL2HUhSOxGYLMg==":"%D0%91%D0%B5%D0%B7%20%D0%BD%D0%B0%D0%B7%D0%B2%D0%B0%D0%BD%D0%B8%D1%8F-304x166.png","uukCy1CbN3TEK35MRAWN0A==":"01_values_honeycomb_white-red-2000x1094.png","vVvx67jHrTRdRLQucRwBUw==":"sm-logo-header-600x578.png","cj4GfpfLkkTOKXswt5Y1IQ==":"sm-logo-header-192x185.png","bdik1vFSti8GNJlRbQHtEg==":"bg_world-1195x620.png","rdnfcXnZBW2G8YX9J8MxRQ==":"top_shop-128x40.png","nokWs4PrqJ22U58vk5bgvA==":"delimano-128x40.png","bE9im+kswwMq4MshjTPwKA==":"dormeo-128x40.png","0pLYATiEVMgGQZgmMjKRWA==":"rovus-128x40.png","97jSuHXVGSw3XM+RRWIYyA==":"walkmaxx-128x40.png","8iknAGmIjD7FfL74m4/rZg==":"top_shop_color-128x40.png","mXjNAOK1XhA3Wa1nyWxLdQ==":"face6.jpg","DOy/nUpdD3oxyuIasbfwJg==":"face6-1.jpg","m8QuHYvdJYsSsCH9NbS5QQ==":"face6-2.jpg","rhKkPrw2b4zxcAwTcbqcqQ==":"23658891_1978014565746367_6989474160821187250_n-110x110.jpg","dxse0NVgLaEeu132eqyyzA==":"20708254_1935741669973657_665669327469275959_n-110x110.jpg","0SO9qJHcjoJjQHHjYt7p2A==":"sm_corpo_brands_dormeo_2_desna_mango2-1080x569.jpg","NrvF2ipy8wvJJyH7zARsXg==":"090848-1419401328-800x1024.png","VlI9zxZ9mLLHaxQkrjEaCw==":"bg_world-1-1195x620.png","qD7AsfCekOGhwwquqwfIpw==":"090848-1419401329-800x1024.png","OAFCM4DRcWXxbHqYQeQH4A==":"01_values_honeycomb_white-red-1776x972.png","v5IJL0qaJPCa+o6gXLB9aQ==":"bg_world-2-1195x620.png","qRtQYLYNp3SHx6WEZFDPKA==":"untitled-info-500x500.jpg","xBG/AGZKZl5PCu/pyC53kw==":"front3-2000x1319.png","WVtgVv1o2FGUvn7tbQ/ERA==":"bg_people_standing-1920x866.jpg","M9gttCIYNivIE+RIZhwsxw==":"bg_people_standing-1-1920x866.jpg","vupswQWCmYzzgJnvGdweFA==":"istock_000049625510xweb-500x354.gif","ihlkf69UyfSmhSyJ1Jvc6w==":"jumbotron.jpg","9sZeY/+stJloULJ3kKJdxg==":"01_values_honeycomb_white-red-2220x1215.png","gtBZIZD+2/vSdGf76uz2mA==":"sm-logo-header-444x428.png","ugOQo6NDE60EtF2/YZRiIw==":"frooon-5-2000x2000.png","x74y53Iv9Q5eX3FoTwSUHQ==":"untitled-5-2000x2000.png","aBfkfWslNi3nriktDMRKEw==":"videoblocks-geometric-red-lines-background_rn-2lwd5x_thumbnail-full01-1920x1080.png","p6W/FrLdH7J8F3aWmIz93w==":"videoblocks-geometric-red-lines-background_rn-2lwd5x_thumbnail-full01-1-1920x1080.png","y0JCwrQBNSCXUGgvGJSV3A==":"front3-1-2000x1319.png","cYIJi8nUu+slo3fwVBcoNw==":"videoblocks-geometric-red-lines-background_rn-2lwd5x_thumbnail-full01-2-1920x1080.png","lcfFUEPYSz4hykYoP2x0fQ==":"front3-2-2000x1319.png","vuMdM+j8h3V1z2SftSowHg==":"front3-3-2000x1319.png","5VN7qTKnWwQviXq0W52J8Q==":"layer9-1920x929.png","iE0ZQ2vDZ+yhuaE1NRi3sA==":"check-100x100.png","EzL5F1TU2O1KWPxaof8ZCg==":"face3.jpg","AeFJGgq2rzF4VGbmKET5wQ==":"istock_000049625510xweb-1-500x354.gif","/sTspN6eX1RwS6+1MNQsRw==":"istock_000049625510xweb-2-500x354.gif","arRbRy2jn+t3ztdP8j2XJw==":"bg_dormeo-1920x780.jpg","GTarLFK1GbDVWODmeoEJRw==":"bg_walkmaxx-2000x920.jpg","xiyJo3PH0ggYY4gptA/b/w==":"sm_corpo_brands_rovus_2_desna-web-2000x1053.jpg","LiAXtRBI/wnMT01qmk3alg==":"sm_corpo_brands_delimano_1_desna-1784x990.jpg","mlAFqA0P5vAbAxkD1h39NA==":"brisbane-headshots-commercial-photography-9-1920x1080.jpg","HVcpNJL4lFZCP6UjWWNMeg==":"katie-3125-2000x2806.jpg","SDzmm3VqoP0kXK+QEwDgBw==":"brisbane-headshots-commercial-photography-10-1920x1080.jpg","bsU+nrdYHjc279tz8bo2qw==":"katie-3126-2000x2806.jpg","2OoG5akdxvWX1+wWVobgdg==":"katie-3127-2000x2806.jpg","oZ+kLgnekeVVrkkghf2CZw==":"img-1022-2000x1500.png","IpAZyBr049adcSO4CrY6cw==":"img-1023-2000x1500.png","041b5REcMPI+e2AWB6/w5A==":"mbr-1-720x1080.jpg","VYKdXkCbtcAMWV10cQhmyg==":"cg-corporate-contact-centres-rct-lowres-1920x1080.jpg","Mzbiu/y56gjZH0vfCLShTQ==":"bgvideo-1920x1080.jpg","RNZXOadkOvi+ENmNsoEWeA==":"customer-service-call-center-2000x1299.jpg","NpsfuKRK1rhY9H8fvc1R2Q==":"front3-4-2000x1319.png","6I3wE3Jd7UxwtA4YMhhZ+g==":"front3-5-2000x1319.png","SgxWjl0J5h9Y3+LeqaKY8Q==":"sdsdddfrontback%202%20bv-2000x1400.png","IUSZupSiDP6cmnsiy5cLiA==":"female-512x512.png","/151pXdmIKDiT/x9yV7bog==":"female-1-512x512.png","adWzHWVfQ5a+lzKzEd1dJw==":"mbr-717x1080.jpg","AsQr5QMDIMlzhGPNv2mjWQ==":"female-2-512x512.png","xe+kj3xOVRvtKq3mVd7T5g==":"female-3-512x512.png","sCeNF3DOqvpjKuOugT9/VA==":"katie-3125-930x1305.jpg","3C4kqnmzCxXP7PbttKnnqw==":"katie-3126-930x1305.jpg","JZv6bzvqjXGvp6MisTNo8Q==":"brisbane-headshots-commercial-photography-9-1200x675.jpg","YV/juBhUh2hp4o93FgOB5A==":"katie-3127-930x1305.jpg","LiUIORYxGXGMpCM1i0NnEA==":"06.jpg","4+DzqXFpj/z2AIwVP9lcYQ==":"background5.jpg","2IZzlc2fWl1VZKyDJfmTSQ==":"brisbane-headshots-commercial-photography-10-1200x675.jpg","2a4G2RNeErQ/8n3eWbMKrQ==":"politica-atencion-cliente-780x475.jpg","/koy+Rab7W4O7Gi6Z/oOLQ==":"untitled-235x371.png","x+uEoN957NDQF6C8rd0L4Q==":"untitled-1-235x371.png","B/p3c2O/mb8zDFL79Xn03g==":"mbr-1396x1080.jpg","7rCWJtnIzNE5HrVuYLlrBw==":"wp1912957-982x687.png","0OOE1Usrtktm437Z/qTMRQ==":"background2.jpg","i8YX1buBtuPhfA/wpoOimQ==":"dollarphotoclub-87612113-672x403.jpg","ZViHCp6DxUE3ESiztbNgiA==":"dollarphotoclub-87612113-2000x1200.jpg","52NrsK2KB3OX8iLTCo1tuA==":"wp1912957-2000x1400.png","TEJGL+IgtdTuy86F8nMVUw==":"img-54-1200x800.png","WcNJ8SGZPocwlfNX2kyJ0w==":"img-60-1200x800.png","XNSqyXchFgx244LDCWdwdA==":"img-64-1200x800.png","nWF7wfPqQTbavtYFu3lKgg==":"img-72-1096x731.png","dg2mERJpPOHVqaz/wHhd4A==":"img-79-660x440.png","wc1h/fdJZqBxQb7LC6k/Wg==":"img-80-660x440.png","uwZJZf2xsh2Xum8E6iSONA==":"img-79-878x585.png","8DOJU2YJx7JyMTV5DvAbTA==":"img-64-1020x680.png","28spDIIm+CVFrnUjMk4UAw==":"img-72-1200x800.png","pF4+BFKatrGyskvtTViI6Q==":"img-79-676x451.png","4jhRgtb64NmuYbsmCt1duw==":"img-54-676x451.png","gqj+LS9qRa/t86Qzu8vE5g==":"img-60-676x451.png","xcsQW6WaXitZp0L+JoRzLg==":"girl-808x808.jpg","RUyji0wsTxu0RUnPeSDx1A==":"cat-as-a-user-1200x1200.jpg","8rKIuZeWWC9+2JSXaCl+oA==":"ayo-ogunseinde-316141-3333x3333.jpg","bwn2y6eYzAo42v1WuqjZaQ==":"mike-wilson-253599-2189x2189.jpg","VewxTI09xUxfFfWGYXQJBQ==":"img-64-510x340.png","DIz5wQpxS9joXPlQWlXxdw==":"img-65-510x340.png","P9+5zBqCDxkY50pGmp9Slw==":"img-72-510x340.png","gwo3SROggFz87c9B6mk5wA==":"img-99-510x340.png","DRCvwj/UPxnvGf7GWiJhLA==":"img-73-510x340.png","tHw2WW4nUHM9D3MPBJ36kA==":"img-66-510x340.png","5Gmj00/PaFJS7mhyZz71cw==":"img-87-510x340.png","nPVn2XTYbDvg5LL/Gj1XhA==":"img-72-2000x1333.png","E2ag+6kumQOBja7UT5WuyA==":"img-64-2000x1333.png","q3ShwR91eCrNGmfefAgTqA==":"img-87-2000x1333.png","SRuUMxOwK9m2ZgL+Ekk6jA==":"img-99-2000x1333.png","FuwPoh0qDeCcYg1brKUGuQ==":"img-64-676x451.png","Z+crPtURWioLFA1i30fytg==":"img-72-950x633.png"}